swekit/__init__.py
swekit/__main__.py
swekit/cli.py
swekit/exceptions.py
swekit/py.typed
swekit/agents/__init__.py
swekit/agents/base.py
swekit/benchmark/__init__.py
swekit/benchmark/complete_eval_workflow.sh
swekit/benchmark/constants.py
swekit/benchmark/get_score_card.py
swekit/benchmark/run_evaluation.py
swekit/benchmark/setup_test_bed.py
swekit/benchmark/utils.py
swekit/benchmark/visualize.py
swekit/benchmark/docker_utils/THIRD-PARTY-LICENSE
swekit/benchmark/docker_utils/__init__.py
swekit/benchmark/docker_utils/evaulate_on_docker.py
swekit/benchmark/docker_utils/docker/Dockerfile.swe_agent
swekit/benchmark/docker_utils/docker_file_generator/__init__.py
swekit/benchmark/docker_utils/docker_file_generator/const.py
swekit/benchmark/docker_utils/docker_file_generator/context_manager.py
swekit/benchmark/docker_utils/docker_file_generator/docker_file_generator.py
swekit/benchmark/docker_utils/docker_file_generator/evaluate_instance.py
swekit/benchmark/docker_utils/docker_file_generator/run_docker.py
swekit/benchmark/docker_utils/docker_file_generator/utils.py
swekit/benchmark/docker_utils/scripts/build_docker_images.sh
swekit/benchmark/docker_utils/scripts/docker_push.sh
swekit/benchmark/docker_utils/templates/Dockerfile.base
swekit/benchmark/docker_utils/templates/Dockerfile.pyenv_instance
swekit/benchmark/docker_utils/templates/Dockerfile.swe
swekit/benchmark/docker_utils/templates/getconda.sh
swekit/benchmark/docker_utils/templates/install_composio.sh
swekit/config/__init__.py
swekit/config/constants.py
swekit/config/context.py
swekit/config/store.py
swekit/scaffold/__init__.py
swekit/scaffold/_scaffold.py
swekit/scaffold/templates/__init__.py
swekit/scaffold/templates/pr_review/crewai/custom_tools.template
swekit/scaffold/templates/pr_review/crewai/main.template
swekit/scaffold/templates/pr_review/langgraph/agent.template
swekit/scaffold/templates/pr_review/langgraph/inputs.template
swekit/scaffold/templates/pr_review/langgraph/main.template
swekit-0.4.18.dist-info/METADATA
swekit-0.4.18.dist-info/WHEEL
swekit-0.4.18.dist-info/entry_points.txt
swekit-0.4.18.dist-info/top_level.txt
swekit-0.4.18.dist-info/RECORD
