Metadata-Version: 2.4
Name: swekit
Version: 0.4.18
Summary: Tools for running a SWE agent using Composio platform
Home-page: https://github.com/composiohq/composio
Author: Shubhra
Author-email: shubhra@composio.dev
Classifier: Programming Language :: Python :: 3
Classifier: License :: OSI Approved :: Apache Software License
Classifier: Operating System :: OS Independent
Requires-Python: >=3.9,<4
Requires-Dist: pydantic>=2.7.4
Requires-Dist: swebench==2.1.0
Requires-Dist: datasets>=2.20.0
Requires-Dist: gitpython>=3.1.43
Requires-Dist: composio_core<0.8.0,>=0.7.0
Requires-Dist: unidiff==0.7.5
Requires-Dist: tqdm==4.66.4
Requires-Dist: rich
Provides-Extra: langgraph
Requires-Dist: langchain-aws==0.1.17; extra == "langgraph"
Requires-Dist: langgraph>=0.2.16; extra == "langgraph"
Requires-Dist: langgraph-prebuilt>=0.1.0; extra == "langgraph"
Requires-Dist: composio_langgraph<0.8.0,>=0.5.0; extra == "langgraph"
Requires-Dist: python-dotenv==1.0.1; extra == "langgraph"
Dynamic: author
Dynamic: author-email
Dynamic: classifier
Dynamic: description
Dynamic: description-content-type
Dynamic: home-page
Dynamic: provides-extra
Dynamic: requires-dist
Dynamic: requires-python
Dynamic: summary
